{
	"close":false,
	"resourcePlugin":
	{
		"configs":[
		{
			"configPath":"resource/default.res.json",
			"relativePath":"resource/"
		}],
		"id":"org.egret-labs.resource",
		"library":
		{
			"children":[
			{
				"children":[
				{
					"isFolder":false,
					"key":"p1_1",
					"name":"p1_1"
				},
				{
					"isFolder":false,
					"key":"p1_2",
					"name":"p1_2"
				}],
				"isFolder":false,
				"key":"assets_json",
				"name":"assets_json"
			},
			{
				"isFolder":false,
				"key":"bg_jpg",
				"name":"bg_jpg"
			},
			{
				"children":[
				{
					"isFolder":false,
					"key":"p6_1",
					"name":"p6_1"
				},
				{
					"isFolder":false,
					"key":"p6_2",
					"name":"p6_2"
				},
				{
					"isFolder":false,
					"key":"p7_1",
					"name":"p7_1"
				},
				{
					"isFolder":false,
					"key":"p7_2",
					"name":"p7_2"
				},
				{
					"isFolder":false,
					"key":"p8_1",
					"name":"p8_1"
				}],
				"isFolder":false,
				"key":"assets1_json",
				"name":"assets1_json"
			},
			{
				"children":[
				{
					"isFolder":false,
					"key":"g3_1_1",
					"name":"g3_1_1"
				},
				{
					"isFolder":false,
					"key":"g3_1_2",
					"name":"g3_1_2"
				},
				{
					"isFolder":false,
					"key":"g3_1_3",
					"name":"g3_1_3"
				},
				{
					"isFolder":false,
					"key":"g3_2_1",
					"name":"g3_2_1"
				},
				{
					"isFolder":false,
					"key":"g3_2_2",
					"name":"g3_2_2"
				},
				{
					"isFolder":false,
					"key":"g3_2_3",
					"name":"g3_2_3"
				},
				{
					"isFolder":false,
					"key":"g3_3_1",
					"name":"g3_3_1"
				},
				{
					"isFolder":false,
					"key":"g3_3_2",
					"name":"g3_3_2"
				},
				{
					"isFolder":false,
					"key":"g3_3_3",
					"name":"g3_3_3"
				},
				{
					"isFolder":false,
					"key":"g3_4_1",
					"name":"g3_4_1"
				},
				{
					"isFolder":false,
					"key":"g3_4_2",
					"name":"g3_4_2"
				},
				{
					"isFolder":false,
					"key":"g3_4_3",
					"name":"g3_4_3"
				}],
				"isFolder":false,
				"key":"assets2_json",
				"name":"assets2_json"
			}]
		}
	},
	"theme":"resource/default.thm.json"
}